hinteval/__init__.py
hinteval/__version__.py
hinteval/cores/__init__.py
hinteval/cores/dataset_core.py
hinteval/cores/evaluation_core.py
hinteval/cores/model_core.py
hinteval/cores/dataset/dataset.py
hinteval/cores/evaluation_metrics/answer_leakage.py
hinteval/cores/evaluation_metrics/convergence.py
hinteval/cores/evaluation_metrics/familiarity.py
hinteval/cores/evaluation_metrics/readability.py
hinteval/cores/evaluation_metrics/relevance.py
hinteval/cores/model/model.py
hinteval/evaluation/answer_leakage.py
hinteval/evaluation/convergence.py
hinteval/evaluation/familiarity.py
hinteval/evaluation/readability.py
hinteval/evaluation/relevance.py
hinteval/model/__init__.py
hinteval/utils/identify_functions.py
hinteval/utils/convergence/metrics.py
hinteval/utils/convergence/api_based/can_ans_generator.py
hinteval/utils/convergence/api_based/hint_scorer.py
hinteval/utils/convergence/local/can_ans_generator.py
hinteval/utils/convergence/local/hint_scorer.py
hinteval/utils/familiarity/metrics.py
hinteval/utils/familiarity/pageviews.py
hinteval/utils/familiarity/popularity.py
hinteval/utils/functions/download_manager.py
hinteval/utils/functions/ent_spacy.py
hinteval/utils/functions/question_classification.py
hinteval/utils/model/hint_filtering.py
hinteval/utils/model/answer_agnostic/api_based.py
hinteval/utils/model/answer_agnostic/local.py
hinteval/utils/model/answer_aware/api_based.py
hinteval/utils/model/answer_aware/local.py
hinteval/utils/readability/api_based.py
hinteval/utils/readability/local.py
hinteval/utils/relevance/LiteModel.py
hinteval/utils/relevance/relevance_fixed.py
hinteval/utils/relevance/answer_relevancy/api_based.py
hinteval/utils/relevance/answer_relevancy/local.py
hinteval-0.0.6.dist-info/licenses/LICENSE
hinteval-0.0.6.dist-info/METADATA
hinteval-0.0.6.dist-info/WHEEL
hinteval-0.0.6.dist-info/top_level.txt
hinteval-0.0.6.dist-info/RECORD
