Metadata-Version: 2.4
Name: hinteval
Version: 0.0.6
Summary: A Python framework designed for both generating and evaluating hints.
Author-email: Jamshid Mozafari <mozafari.jamshid@gmail.com>
License:                                  Apache License
Project-URL: Documentation, https://hinteval.readthedocs.io/
Project-URL: Repository, https://github.com/DataScienceUIBK/HintEval
Classifier: Development Status :: 2 - Pre-Alpha
Classifier: Environment :: GPU :: NVIDIA CUDA
Classifier: Intended Audience :: Science/Research
Classifier: License :: OSI Approved :: Apache Software License
Classifier: Natural Language :: English
Classifier: Programming Language :: Python :: 3.10
Classifier: Programming Language :: Python :: 3.11
Classifier: Programming Language :: Python :: 3.12
Requires-Python: >=3.10
License-File: LICENSE
Requires-Dist: numpy==1.26.4
Requires-Dist: spacy==3.7.5
Requires-Dist: transformers==4.44.2
Requires-Dist: deepeval==1.3.2
Requires-Dist: instructor==1.5.0
Requires-Dist: outlines==0.2.3
Requires-Dist: pydantic==2.9.1
Requires-Dist: datasets==2.20.0
Requires-Dist: prettytable==3.11.0
Requires-Dist: sentencepiece==0.2.0
Requires-Dist: torchtext==0.2.3
Requires-Dist: lftk==1.0.9
Requires-Dist: joblib==1.4.2
Requires-Dist: xgboost==2.1.0
Requires-Dist: openai==1.45.1
Requires-Dist: nest-asyncio==1.6.0
Requires-Dist: tok==0.1.14
Requires-Dist: rouge-score==0.1.2
Requires-Dist: Faker==26.0.0
Requires-Dist: zipfile-deflate64==0.2.0
Requires-Dist: sentence-transformers==3.0.1
Requires-Dist: accelerate==0.32.1
Requires-Dist: httpx==0.27.2
Dynamic: license-file
